{"cameraMode":{"drawMode":0,"name":"Shaded","section":"Shading Mode"},"sceneLighting":true,"audioPlay":false,"sceneViewState":{"m_AlwaysRefresh":false,"showFog":true,"showSkybox":true,"showFlares":true,"showImageEffects":true,"showParticleSystems":true,"showVisualEffectGraphs":true,"m_FxEnabled":true},"in2DMode":false,"pivot":{"x":0.33127862215042117,"y":-0.2245645672082901,"z":-0.17754226922988892},"rotation":{"x":-0.08717229217290878,"y":0.8995905518531799,"z":-0.21045254170894624,"w":-0.37262260913848879},"size":21.540925979614259,"orthographic":false}